{"nodes": [{"id": "e_ghostai_app_editor_roomid_page_tsx", "label": "page.tsx", "file_type": "code", "source_file": "E:\\ghostai\\app\\editor\\[roomId]\\page.tsx", "source_location": "L1"}, {"id": "roomid_page_editorprojectpageprops", "label": "EditorProjectPageProps", "file_type": "code", "source_file": "E:\\ghostai\\app\\editor\\[roomId]\\page.tsx", "source_location": "L8"}, {"id": "roomid_page_editorprojectpage", "label": "EditorProjectPage()", "file_type": "code", "source_file": "E:\\ghostai\\app\\editor\\[roomId]\\page.tsx", "source_location": "L14"}], "edges": [{"source": "e_ghostai_app_editor_roomid_page_tsx", "target": "navigation", "relation": "imports_from", "context": "import", "confidence": "EXTRACTED", "source_file": "E:\\ghostai\\app\\editor\\[roomId]\\page.tsx", "source_location": "L1", "weight": 1.0}, {"source": "e_ghostai_app_editor_roomid_page_tsx", "target": "e_ghostai_components_editor_access_denied_tsx", "relation": "imports_from", "context": "import", "confidence": "EXTRACTED", "source_file": "E:\\ghostai\\app\\editor\\[roomId]\\page.tsx", "source_location": "L3", "weight": 1.0}, {"source": "e_ghostai_app_editor_roomid_page_tsx", "target": "editor_access_denied_accessdenied", "relation": "imports", "context": "import", "confidence": "EXTRACTED", "source_file": "E:\\ghostai\\app\\editor\\[roomId]\\page.tsx", "source_location": "L3", "weight": 1.0}, {"source": "e_ghostai_app_editor_roomid_page_tsx", "target": "e_ghostai_components_editor_editor_workspace_client_tsx", "relation": "imports_from", "context": "import", "confidence": "EXTRACTED", "source_file": "E:\\ghostai\\app\\editor\\[roomId]\\page.tsx", "source_location": "L4", "weight": 1.0}, {"source": "e_ghostai_app_editor_roomid_page_tsx", "target": "editor_editor_workspace_client_editorworkspaceclient", "relation": "imports", "context": "import", "confidence": "EXTRACTED", "source_file": "E:\\ghostai\\app\\editor\\[roomId]\\page.tsx", "source_location": "L4", "weight": 1.0}, {"source": "e_ghostai_app_editor_roomid_page_tsx", "target": "e_ghostai_lib_project_access_ts", "relation": "imports_from", "context": "import", "confidence": "EXTRACTED", "source_file": "E:\\ghostai\\app\\editor\\[roomId]\\page.tsx", "source_location": "L5", "weight": 1.0}, {"source": "e_ghostai_app_editor_roomid_page_tsx", "target": "lib_project_access_checkprojectaccess", "relation": "imports", "context": "import", "confidence": "EXTRACTED", "source_file": "E:\\ghostai\\app\\editor\\[roomId]\\page.tsx", "source_location": "L5", "weight": 1.0}, {"source": "e_ghostai_app_editor_roomid_page_tsx", "target": "lib_project_access_getcurrentuseridentity", "relation": "imports", "context": "import", "confidence": "EXTRACTED", "source_file": "E:\\ghostai\\app\\editor\\[roomId]\\page.tsx", "source_location": "L5", "weight": 1.0}, {"source": "e_ghostai_app_editor_roomid_page_tsx", "target": "lib_project_access_getsigninpath", "relation": "imports", "context": "import", "confidence": "EXTRACTED", "source_file": "E:\\ghostai\\app\\editor\\[roomId]\\page.tsx", "source_location": "L5", "weight": 1.0}, {"source": "e_ghostai_app_editor_roomid_page_tsx", "target": "e_ghostai_lib_project_data_ts", "relation": "imports_from", "context": "import", "confidence": "EXTRACTED", "source_file": "E:\\ghostai\\app\\editor\\[roomId]\\page.tsx", "source_location": "L6", "weight": 1.0}, {"source": "e_ghostai_app_editor_roomid_page_tsx", "target": "lib_project_data_geteditorprojectsforcurrentuser", "relation": "imports", "context": "import", "confidence": "EXTRACTED", "source_file": "E:\\ghostai\\app\\editor\\[roomId]\\page.tsx", "source_location": "L6", "weight": 1.0}, {"source": "e_ghostai_app_editor_roomid_page_tsx", "target": "roomid_page_editorprojectpageprops", "relation": "contains", "confidence": "EXTRACTED", "source_file": "E:\\ghostai\\app\\editor\\[roomId]\\page.tsx", "source_location": "L8", "weight": 1.0}, {"source": "e_ghostai_app_editor_roomid_page_tsx", "target": "roomid_page_editorprojectpage", "relation": "contains", "confidence": "EXTRACTED", "source_file": "E:\\ghostai\\app\\editor\\[roomId]\\page.tsx", "source_location": "L14", "weight": 1.0}], "raw_calls": [{"caller_nid": "roomid_page_editorprojectpage", "callee": "getCurrentUserIdentity", "is_member_call": false, "source_file": "E:\\ghostai\\app\\editor\\[roomId]\\page.tsx", "source_location": "L19"}, {"caller_nid": "roomid_page_editorprojectpage", "callee": "redirect", "is_member_call": false, "source_file": "E:\\ghostai\\app\\editor\\[roomId]\\page.tsx", "source_location": "L21"}, {"caller_nid": "roomid_page_editorprojectpage", "callee": "getSignInPath", "is_member_call": false, "source_file": "E:\\ghostai\\app\\editor\\[roomId]\\page.tsx", "source_location": "L21"}, {"caller_nid": "roomid_page_editorprojectpage", "callee": "checkProjectAccess", "is_member_call": false, "source_file": "E:\\ghostai\\app\\editor\\[roomId]\\page.tsx", "source_location": "L25"}, {"caller_nid": "roomid_page_editorprojectpage", "callee": "getEditorProjectsForCurrentUser", "is_member_call": false, "source_file": "E:\\ghostai\\app\\editor\\[roomId]\\page.tsx", "source_location": "L33"}]}